blatt/__init__.py
blatt/cli.py
blatt/page.py
blatt-0.1.6.dist-info/LICENSE
blatt-0.1.6.dist-info/METADATA
blatt-0.1.6.dist-info/WHEEL
blatt-0.1.6.dist-info/entry_points.txt
blatt-0.1.6.dist-info/top_level.txt
blatt-0.1.6.dist-info/RECORD
