Metadata-Version: 2.1
Name: blatt
Version: 0.1.6
Summary: NLP-helper for OCR-ed pages in PAGE XML format.
Home-page: https://github.com/UB-Mannheim/blatt
Author: Renat Shigapov
License: MIT
Classifier: Programming Language :: Python :: 3
Classifier: License :: OSI Approved :: MIT License
Classifier: Operating System :: OS Independent
Requires-Python: >=3.7
License-File: LICENSE
Requires-Dist: lxml
Requires-Dist: tqdm
Requires-Dist: click
Requires-Dist: segtok
